oshino_consul/__init__.py
oshino_consul/agent.py
oshino_consul/version.py
oshino_consul-0.1.2.dist-info/DESCRIPTION.rst
oshino_consul-0.1.2.dist-info/METADATA
oshino_consul-0.1.2.dist-info/RECORD
oshino_consul-0.1.2.dist-info/WHEEL
oshino_consul-0.1.2.dist-info/metadata.json
oshino_consul-0.1.2.dist-info/top_level.txt
