Metadata-Version: 2.0
Name: oshino-consul
Version: 0.1.2
Summary: Agent for retrieving consul stats
Home-page: UNKNOWN
Author: zaibacu
Author-email: UNKNOWN
License: UNKNOWN
Platform: UNKNOWN
Requires-Dist: oshino
